menu_cli/__init__.py
menu_cli/core.py
menu_cli/fzf.py
menu_cli/utils.py
fuzzy_menu_cli-0.0.2.dist-info/LICENSE
fuzzy_menu_cli-0.0.2.dist-info/METADATA
fuzzy_menu_cli-0.0.2.dist-info/WHEEL
fuzzy_menu_cli-0.0.2.dist-info/entry_points.txt
fuzzy_menu_cli-0.0.2.dist-info/top_level.txt
fuzzy_menu_cli-0.0.2.dist-info/RECORD
